LICENCE.txt
MANIFEST.in
README.txt
setup.py
test.py
goldy_smart_house/__init__.py
goldy_smart_house/cache.py
goldy_smart_house/client.py
goldy_smart_house/commands.py
goldy_smart_house/google_nest_controller.py
goldy_smart_house/events/__init__.py
goldy_smart_house/events/_on_command_.py
goldy_smart_house/methods/__init__.py
goldy_smart_house/methods/dropbox.py
goldy_smart_house/objects/__init__.py
goldy_smart_house/objects/command.py
goldy_smart_house/utility/__init__.py
goldy_smart_house/utility/logging.py
goldysmarthouse.egg-info/PKG-INFO
goldysmarthouse.egg-info/SOURCES.txt
goldysmarthouse.egg-info/dependency_links.txt
goldysmarthouse.egg-info/requires.txt
goldysmarthouse.egg-info/top_level.txt