Metadata-Version: 2.1
Name: goldysmarthouse
Version: 2.0
Summary: A shity python module that allows a Google Assistant device (Google Home, etc) to run code on your computer.
Home-page: 
Author: Dev Goldy
Author-email: goldy@novauniverse.net
License: MIT
Project-URL: Bug Tracker, https://github.com/THEGOLDENPRO/Goldy-Smart-House/issues
Keywords: goldysmarthouse,goldy smart house,smart goldy house,google home,google assistant,google home client
Classifier: Operating System :: Microsoft :: Windows :: Windows 10
Classifier: Operating System :: POSIX :: Linux
Classifier: License :: OSI Approved :: MIT License
Classifier: Programming Language :: Python :: 3.7
Classifier: Programming Language :: Python :: 3.8
Classifier: Programming Language :: Python :: 3.9
Requires-Python: >=3.7
License-File: LICENCE.txt
